[
    {
        "ImageName": "1.2.40.0.13.1.115575674563845685276951436274006804168-label-lesion", 
        "Scores": [
            {
                "AgatstonScore": 4151.176071166994, 
                "NAME": "AGATSTON", 
                "Grading": "severe", 
                "LAD": 1465.0497436523442, 
                "RCA": 1531.6429138183598, 
                "LCX": 1154.4834136962895
            }
        ]
    }, 
    {
        "ImageName": "1.2.40.0.13.1.157195166742609778052460343332092430042-label-lesion", 
        "Scores": [
            {
                "AgatstonScore": 1012.2528076171875, 
                "NAME": "AGATSTON", 
                "Grading": "severe", 
                "LAD": 619.95849609375, 
                "RCA": 25.58441162109375, 
                "LCX": 366.70989990234375
            }
        ]
    }
]